<?xml version="1.0" encoding="utf-8"?>
<odoo>
    <data>
        <record id="edit_holiday_new" model="ir.ui.view">
            <field name="name">Leave Request (hr_holidays_working_time)</field>
            <field name="model">hr.holidays</field>
            <field name="inherit_id" ref="hr_holidays.edit_holiday_new" />
            <field name="arch" type="xml">
                <xpath expr="//div[field[@name='number_of_days_temp']]" position="before">
                    <div invisible="context.get('default_type', 'x') == 'add'">
                        <field name="set_hours_manually" class="oe_inline"/>
                        <label for="set_hours_manually" class="oe_inline" />
                    </div>
                    <div attrs="{'invisible': [('set_hours_manually', '=', True)]}">
                        <field name="number_of_hours_temp" class="oe_inline"/> hours
                    </div>
                    <div attrs="{'invisible': [('set_hours_manually', '=', False)]}">
                        <field name="number_of_hours_temp_manual" class="oe_inline"/> hours
                    </div>
                </xpath>
                <xpath expr="//field[@name='number_of_days_temp']" position="attributes">
                    <attribute name="readonly">1</attribute>
                </xpath>
            </field>
        </record>
        <record model="ir.ui.view" id="view_holiday">
            <field name="name">hr.holidays.tree (ir.ui.view)</field>
            <field name="model">hr.holidays</field>
            <field name="inherit_id" ref="hr_holidays.view_holiday" />
            <field name="arch" type="xml">
                <field name="number_of_days" position="before">
                    <field name="number_of_hours" string="Number of hours" />
                </field>
            </field>
        </record>
        <record model="ir.ui.view" id="view_holiday_simple">
            <field name="name">hr.holidays.report_tree</field>
            <field name="model">hr.holidays</field>
            <field name="inherit_id" ref="hr_holidays.view_holiday_simple" />
            <field name="arch" type="xml">
                <field name="number_of_days" position="before">
                    <field name="number_of_hours" string="Number of hours" sum="Number of hours" />
                </field>
            </field>
        </record>
        <record model="ir.ui.view" id="view_holiday_employee">
            <field name="name">hr.holidays.tree</field>
            <field name="model">hr.holidays</field>
            <field name="inherit_id" ref="hr_holidays.view_holiday_employee" />
            <field name="arch" type="xml">
                <field name="number_of_days" position="before">
                    <field name="number_of_hours" string="Number of hours" />
                </field>
            </field>
        </record>
        <record model="ir.ui.view" id="view_holiday_allocation_tree">
            <field name="name">hr.holidays.allocation.tree</field>
            <field name="model">hr.holidays</field>
            <field name="inherit_id" ref="hr_holidays.view_holiday_allocation_tree" />
            <field name="arch" type="xml">
                <field name="number_of_days" position="before">
                    <field name="number_of_hours" string="Allocated Hours" />
                </field>
            </field>
        </record>
    </data>
</odoo>